{"edges": [[18, 9], [9, 18], [18, 9], [9, 18], [18, 9], [9, 18], [18, 9], [9, 18], [18, 9], [9, 18], [18, 9], [9, 18], [18, 9], [9, 18], [18, 9], [9, 18], [18, 9], [9, 18], [18, 9], [9, 18], [9, 18], [18, 9], [9, 18], [18, 9], [9, 18], [18, 9], [9, 18], [18, 9], [9, 18], [18, 9], [9, 18], [18, 9], [9, 18], [18, 9], [9, 18], [18, 9], [9, 18], [18, 9], [9, 18], [18, 9], [9, 18], [18, 9], [9, 18], [18, 9], [9, 18], [18, 9], [18, 9], [9, 18], [18, 9], [9, 18], [18, 9], [9, 18], [18, 9], [9, 18], [18, 9], [9, 18], [18, 9], [9, 18], [18, 9], [9, 18], [18, 9], [9, 18], [18, 9], [9, 18], [18, 9], [9, 18], [18, 9], [9, 18], [18, 9], [9, 18], [9, 18], [18, 9], [9, 18], [18, 9], [9, 18], [18, 9], [9, 18], [18, 9], [9, 18], [18, 9], [9, 18], [18, 9], [9, 18], [18, 9], [9, 18], [18, 9], [9, 18], [18, 9], [9, 18], [18, 9], [9, 18], [18, 9], [18, 9], [9, 18], [18, 9], [9, 18], [18, 9], [9, 18], [18, 9], [9, 18], [18, 9], [9, 18], [18, 9], [9, 18], [18, 9], [9, 18], [18, 9], [9, 18], [18, 9], [9, 18], [18, 9], [9, 18], [18, 9], [9, 18], [18, 9], [9, 18], [18, 9], [9, 18], [18, 9], [9, 18], [9, 18], [18, 9], [9, 18], [18, 9], [9, 18], [18, 9], [18, 9], [9, 18], [18, 9], [9, 18], [18, 9], [9, 18], [18, 9], [9, 18], [9, 18], [18, 9], [9, 18], [18, 9], [9, 18], [18, 9], [9, 18], [18, 9], [9, 18], [18, 9], [9, 18], [18, 9], [9, 18], [18, 9], [9, 18], [18, 9], [9, 18], [18, 9], [9, 18], [18, 9], [9, 18], [18, 9], [9, 18], [18, 9], [9, 18], [18, 9], [9, 18], [18, 9], [9, 18], [18, 9], [9, 18], [18, 9], [9, 18], [18, 9], [18, 9], [9, 18], [18, 9], [9, 18], [18, 9], [9, 18], [18, 9], [9, 18], [18, 9], [9, 18], [18, 9], [9, 18], [18, 9], [9, 18], [18, 9], [9, 18], [18, 9], [9, 18], [18, 9], [9, 18], [18, 9], [9, 18], [18, 9], [9, 18], [18, 9], [9, 18], [18, 9], [9, 18], [18, 9], [9, 18], [18, 9], [9, 18], [18, 9], [9, 18], [18, 9], [9, 18], [18, 9], [9, 18], [18, 9], [9, 18], [18, 9], [9, 18], [18, 9], [9, 18], [18, 9], [9, 18], [18, 9], [9, 18], [18, 9], [9, 18], [18, 9], [9, 18], [18, 9], [9, 18], [18, 9], [9, 18], [18, 9], [9, 18], [18, 9], [9, 18], [18, 9], [9, 18], [18, 9], [9, 18], [18, 9], [9, 18], [18, 9], [9, 18], [18, 9], [9, 18], [18, 9], [9, 18], [18, 9], [9, 18], [18, 9], [9, 18], [18, 9], [9, 18], [18, 9], [9, 18], [18, 9], [9, 18], [18, 9], [9, 18], [18, 9], [9, 18], [18, 9], [9, 18], [18, 9], [9, 18], [9, 18], [18, 9], [9, 18], [18, 9], [9, 18], [18, 9], [9, 18], [18, 9], [9, 18], [18, 9], [9, 18], [18, 9], [9, 18], [18, 9], [9, 18], [18, 9], [9, 18], [18, 9], [9, 18], [18, 9], [9, 18], [18, 9], [9, 18], [18, 9], [9, 18], [18, 9], [9, 18], [18, 9], [9, 18], [18, 9], [9, 18], [18, 9], [9, 18], [18, 9], [9, 18], [18, 9], [9, 18], [18, 9], [9, 18], [18, 9], [9, 18], [18, 9], [9, 18], [18, 9], [9, 18], [18, 9], [9, 18], [18, 9], [9, 18], [18, 9], [18, 9], [9, 18], [18, 9], [9, 18], [18, 9], [9, 18], [18, 9], [9, 18], [18, 9], [9, 18], [18, 9], [9, 18], [18, 9], [9, 18], [18, 9], [9, 18], [18, 9], [9, 18], [18, 9], [9, 18], [18, 9], [9, 18], [18, 9], [9, 18], [18, 9], [9, 18], [18, 9], [9, 18], [18, 9], [9, 18], [18, 9], [9, 18], [18, 9], [9, 18], [18, 9], [9, 18], [18, 9], [9, 18], [18, 9], [9, 18], [18, 9], [9, 18], [18, 9], [9, 18], [18, 9], [9, 18], [18, 9], [9, 18], [18, 9], [9, 18], [9, 18], [18, 9], [9, 18], [18, 9], [2, 9], [2, 14], [2, 9], [12, 2], [2, 9], [12, 2], [12, 2], [2, 9], [9, 2], [2, 12], [2, 15], [2, 14], [14, 2], [0, 19], [2, 14], [14, 2], [12, 2], [12, 2], [4, 17], [12, 2], [2, 14], [2, 9], [2, 12], [2, 14], [14, 10], [2, 9], [6, 3], [9, 2], [2, 12], [2, 9], [2, 9], [1, 7], [12, 2], [2, 14], [2, 12], [14, 10], [2, 14], [9, 2], [2, 14], [21, 19], [2, 14], [20, 11], [5, 8], [13, 20], [12, 2], [21, 16], [9, 2], [12, 2], [2, 12], [12, 21], [2, 14], [9, 2], [6, 16], [12, 2]], "features": {"0": "1", "1": "1", "2": "41", "3": "1", "4": "1", "5": "1", "6": "2", "7": "1", "8": "1", "9": "375", "10": "2", "11": "1", "12": "16", "13": "1", "14": "14", "15": "1", "16": "2", "17": "1", "18": "362", "19": "2", "20": "2", "21": "3"}}