{"edges": [[31, 5], [28, 26], [6, 10], [28, 14], [32, 28], [28, 12], [24, 28], [16, 28], [28, 11], [10, 28], [2, 28], [28, 5], [28, 0], [28, 5], [15, 28], [28, 7], [28, 8], [10, 27], [1, 28], [10, 28], [12, 28], [28, 5], [5, 28], [3, 6], [28, 5], [28, 12], [29, 28], [28, 12], [28, 12], [28, 21], [28, 20], [5, 28], [20, 28], [10, 28], [28, 26], [9, 5], [28, 5], [22, 24], [4, 14], [28, 1], [28, 13], [1, 28], [28, 23], [12, 25], [28, 26], [17, 12], [5, 19], [28, 2], [16, 28], [19, 5], [5, 28], [1, 28], [5, 18], [30, 28], [12, 28], [28, 5]], "features": {"0": "1", "1": "4", "2": "2", "3": "1", "4": "1", "5": "14", "6": "2", "7": "1", "8": "1", "9": "1", "10": "5", "11": "1", "12": "8", "13": "1", "14": "2", "15": "1", "16": "2", "17": "1", "18": "1", "19": "2", "20": "2", "21": "1", "22": "1", "23": "1", "24": "2", "25": "1", "26": "3", "27": "1", "28": "44", "29": "1", "30": "1", "31": "1", "32": "1"}}